CONTRIBUTING.md
LICENSE
MANIFEST.in
README.rst
STYLEGUIDE.md
requirements.debian.txt
requirements.txt
setup.cfg
setup.py
ereuse_workbench/__init__.py
ereuse_workbench/benchmark.py
ereuse_workbench/computer.py
ereuse_workbench/erase.py
ereuse_workbench/erwb.py
ereuse_workbench/install.py
ereuse_workbench/snapshot.py
ereuse_workbench/test.py
ereuse_workbench/usb_sneaky.py
ereuse_workbench/utils.py
ereuse_workbench/workbench.py
ereuse_workbench.egg-info/PKG-INFO
ereuse_workbench.egg-info/SOURCES.txt
ereuse_workbench.egg-info/dependency_links.txt
ereuse_workbench.egg-info/entry_points.txt
ereuse_workbench.egg-info/requires.txt
ereuse_workbench.egg-info/top_level.txt
tests/assertions.py
tests/conftest.py
tests/fixtures.sh
tests/test_benchmark.py
tests/test_computer.py
tests/test_erase.py
tests/test_install.py
tests/test_test.py
tests/test_utils.py
tests/test_wrong_computers.py
tests/fixtures/1000h.lshw.json
tests/fixtures/1001pxd.battery.ini
tests/fixtures/1001pxd.hwinfo.txt
tests/fixtures/1001pxd.lshw.json
tests/fixtures/415522G.hwinfo.txt
tests/fixtures/415522G.lshw.json
tests/fixtures/7220w3t.lshw.json
tests/fixtures/7900.hwinfo.txt
tests/fixtures/7900.lshw.json
tests/fixtures/8100.lshw.json
tests/fixtures/TM1613.lshw.json
tests/fixtures/acer-aspire-5737z.lshw.json
tests/fixtures/acer-w500.battery.ini
tests/fixtures/acer-w500.hwinfo.txt
tests/fixtures/acer-w500.lshw.json
tests/fixtures/all-series.lshw.json
tests/fixtures/asus-all-series.lshw.json
tests/fixtures/asus-e200h.battery.ini
tests/fixtures/asus-e200h.hwinfo.txt
tests/fixtures/asus-e200h.lshw.json
tests/fixtures/boxnuc6cayh.hwinfo.txt
tests/fixtures/boxnuc6cayh.lshw.json
tests/fixtures/boxnuc6cayh.snapshot.json
tests/fixtures/core2.lshw.json
tests/fixtures/custom.lshw.json
tests/fixtures/david.lshw.json
tests/fixtures/e5530.battery.ini
tests/fixtures/e5530.hwinfo.txt
tests/fixtures/e5530.lshw.json
tests/fixtures/ecs-2.lshw.json
tests/fixtures/ecs-computers.lshw.json
tests/fixtures/erased-i5.lshw.json
tests/fixtures/erased-i5.snapshot.json
tests/fixtures/hp-pavilion-dv4000.lshw.json
tests/fixtures/lenovo-as-intel.lshw.json
tests/fixtures/lenovo-thinkcentre-edge.lshw.json
tests/fixtures/nec.lshw.json
tests/fixtures/nox.lshw.json
