Metadata-Version: 2.1
Name: ereuse-workbench
Version: 11.0b9
Summary: Hardware report of the computer including components, testing, benchmarking, erasing, and installing an OS.
Home-page: https://github.com/ereuse/workbench
Author: eReuse.org team
Author-email: x.bustamante@ereuse.org
License: Affero
Platform: UNKNOWN
Classifier: Development Status :: 4 - Beta
Classifier: Environment :: Console
Classifier: Intended Audience :: Information Technology
Classifier: Intended Audience :: System Administrators
Classifier: License :: OSI Approved :: GNU Affero General Public License v3
Classifier: Operating System :: POSIX :: Linux
Classifier: Programming Language :: Python
Classifier: Programming Language :: Python :: 3.5
Classifier: Topic :: System :: Logging
Classifier: Topic :: Utilities
Requires-Python: >=3.5.3
Provides-Extra: test
